nengo_bones/__init__.py
nengo_bones/config.py
nengo_bones/templates.py
nengo_bones/version.py
nengo_bones/scripts/__init__.py
nengo_bones/scripts/base.py
nengo_bones/scripts/check_bones.py
nengo_bones/scripts/check_deploy.py
nengo_bones/scripts/format_notebook.py
nengo_bones/scripts/generate_bones.py
nengo_bones/scripts/pr_number.py
nengo_bones/templates/.codecov.yml.template
nengo_bones/templates/.pre-commit-config.yaml.template
nengo_bones/templates/CONTRIBUTING.rst.template
nengo_bones/templates/CONTRIBUTORS.rst.template
nengo_bones/templates/LICENSE.rst.template
nengo_bones/templates/MANIFEST.in.template
nengo_bones/templates/base_script.sh.template
nengo_bones/templates/deploy.sh.template
nengo_bones/templates/docs.sh.template
nengo_bones/templates/examples.sh.template
nengo_bones/templates/pyproject.toml.template
nengo_bones/templates/remote-script.sh.template
nengo_bones/templates/remote.sh.template
nengo_bones/templates/setup.cfg.template
nengo_bones/templates/setup.py.template
nengo_bones/templates/static.sh.template
nengo_bones/templates/test.sh.template
nengo_bones/templates/docs/conf.py.template
nengo_bones/templates/pkg/py.typed.template
nengo_bones/templates/pkg/version.py.template
nengo_bones/tests/__init__.py
nengo_bones/tests/test_check_bones.py
nengo_bones/tests/test_check_deploy.py
nengo_bones/tests/test_ci.py
nengo_bones/tests/test_config.py
nengo_bones/tests/test_format_notebook.py
nengo_bones/tests/test_generate_bones.py
nengo_bones/tests/test_pr_number.py
nengo_bones/tests/utils.py
nengo_bones/tests/ignoreme/__init__.py
nengo_bones/tests/ignoreme/ignoreme.py
nengo_bones/tests/ignoreme/test_norecurse.py
nengo_bones-22.11.15.dist-info/LICENSE.rst
nengo_bones-22.11.15.dist-info/METADATA
nengo_bones-22.11.15.dist-info/WHEEL
nengo_bones-22.11.15.dist-info/entry_points.txt
nengo_bones-22.11.15.dist-info/top_level.txt
nengo_bones-22.11.15.dist-info/RECORD
