Metadata-Version: 2.1
Name: nengo-bones
Version: 22.11.15
Summary: Tools for managing Nengo projects
Home-page: https://www.nengo.ai/nengo-bones
Author: Applied Brain Research
Author-email: info@appliedbrainresearch.com
License: Free for non-commercial use
Classifier: Development Status :: 4 - Beta
Classifier: Framework :: Nengo
Classifier: Intended Audience :: Developers
Classifier: License :: Free for non-commercial use
Classifier: Operating System :: Microsoft :: Windows
Classifier: Operating System :: POSIX :: Linux
Classifier: Programming Language :: Python
Classifier: Programming Language :: Python :: 3.6
Classifier: Programming Language :: Python :: 3.7
Classifier: Programming Language :: Python :: 3.8
Classifier: Programming Language :: Python :: 3.9
Classifier: Topic :: Software Development
Requires-Python: >=3.6
License-File: LICENSE.rst
Requires-Dist: black (>=21.12b0)
Requires-Dist: click (>=7.0)
Requires-Dist: codespell (>=2.0.0)
Requires-Dist: docformatter (>=1.5.0)
Requires-Dist: flake8 (>=3.7.7)
Requires-Dist: jinja2 (>=2.11)
Requires-Dist: jupyter (>=1.0.0)
Requires-Dist: pylint (>=2.5.1)
Requires-Dist: pyyaml (>=5.1)
Requires-Dist: requests (>=2.21)
Provides-Extra: all
Requires-Dist: check-manifest (>=0.48) ; extra == 'all'
Provides-Extra: docs
Provides-Extra: optional
Provides-Extra: tests
Requires-Dist: check-manifest (>=0.48) ; extra == 'tests'
